adrift/__init__.py
adrift-0.0.1.dist-info/METADATA
adrift-0.0.1.dist-info/WHEEL
adrift-0.0.1.dist-info/RECORD
